{"inputPath":"D:\\Development\\robot-commando\\_book\\i.038.jpg","crop":{"x":0,"y":0,"width":636,"height":1076,"scale":2,"threshold":-1},"text":"94-97 94 The stairway leads to a corridor which turns down- ward once again. Eventually, the corridor ends in a small alcove with a lift. Rather than retrace your steps, you enter the lift and push the button. Turn to 44. 95 This is a fatal mistake: you quickly sink into the swampy goo. The dinosaur watches, bemused, as bubbles rise to mark your resting-place. 96 In trying to open an Office marked 'Private', you activate a security system. An electric shock pins you to the door-frame. By the time you get free, you have lost STAMINA point. Return to 85. 97 battle is over. You have torn the Man-trap Plant into a thousand pieces. Nothing remains of the vicious vegetable except a damper spot on the marshy ground. Turn to 237.","lines":[{"text":"94-97","left":99,"top":70,"words":[{"text":"94-97","left":99,"top":70,"width":62,"height":19}]},{"text":"94","left":351,"top":123,"words":[{"text":"94","left":351,"top":123,"width":23,"height":19}]},{"text":"The stairway leads to a corridor which turns down-","left":99,"top":144,"words":[{"text":"The","left":99,"top":144,"width":41,"height":19},{"text":"stairway","left":145,"top":145,"width":88,"height":25},{"text":"leads","left":239,"top":145,"width":54,"height":19},{"text":"to","left":298,"top":147,"width":21,"height":17},{"text":"a","left":323,"top":150,"width":12,"height":14},{"text":"corridor","left":340,"top":145,"width":84,"height":19},{"text":"which","left":429,"top":145,"width":62,"height":19},{"text":"turns","left":497,"top":147,"width":54,"height":18},{"text":"down-","left":556,"top":145,"width":68,"height":20}]},{"text":"ward once again. Eventually, the corridor ends in a","left":100,"top":171,"words":[{"text":"ward","left":100,"top":171,"width":53,"height":19},{"text":"once","left":159,"top":177,"width":48,"height":14},{"text":"again.","left":212,"top":172,"width":62,"height":25},{"text":"Eventually,","left":282,"top":171,"width":115,"height":26},{"text":"the","left":405,"top":172,"width":32,"height":19},{"text":"corridor","left":442,"top":172,"width":84,"height":19},{"text":"ends","left":531,"top":172,"width":50,"height":19},{"text":"in","left":586,"top":173,"width":19,"height":18},{"text":"a","left":611,"top":177,"width":12,"height":14}]},{"text":"small alcove with a lift. Rather than retrace your","left":99,"top":198,"words":[{"text":"small","left":99,"top":198,"width":56,"height":19},{"text":"alcove","left":163,"top":199,"width":67,"height":18},{"text":"with","left":239,"top":199,"width":47,"height":18},{"text":"a","left":295,"top":203,"width":12,"height":14},{"text":"lift.","left":317,"top":198,"width":34,"height":19},{"text":"Rather","left":362,"top":199,"width":69,"height":18},{"text":"than","left":441,"top":199,"width":46,"height":18},{"text":"retrace","left":497,"top":202,"width":69,"height":16},{"text":"your","left":575,"top":204,"width":49,"height":20}]},{"text":"steps, you enter the lift and push the button. Turn to","left":99,"top":228,"words":[{"text":"steps,","left":99,"top":228,"width":61,"height":23},{"text":"you","left":165,"top":231,"width":40,"height":20},{"text":"enter","left":208,"top":228,"width":55,"height":17},{"text":"the","left":267,"top":225,"width":32,"height":20},{"text":"lift","left":303,"top":225,"width":27,"height":20},{"text":"and","left":334,"top":226,"width":39,"height":19},{"text":"push","left":377,"top":226,"width":51,"height":25},{"text":"the","left":433,"top":226,"width":33,"height":19},{"text":"button.","left":469,"top":226,"width":74,"height":19},{"text":"Turn","left":548,"top":226,"width":51,"height":19},{"text":"to","left":603,"top":229,"width":20,"height":16}]},{"text":"44.","left":99,"top":258,"words":[{"text":"44.","left":99,"top":258,"width":30,"height":19}]},{"text":"95","left":350,"top":311,"words":[{"text":"95","left":350,"top":311,"width":23,"height":20}]},{"text":"This is a fatal mistake: you quickly sink into the","left":99,"top":333,"words":[{"text":"This","left":99,"top":333,"width":46,"height":20},{"text":"is","left":154,"top":333,"width":17,"height":20},{"text":"a","left":180,"top":339,"width":12,"height":14},{"text":"fatal","left":203,"top":333,"width":43,"height":20},{"text":"mistake:","left":257,"top":333,"width":86,"height":20},{"text":"you","left":353,"top":339,"width":39,"height":20},{"text":"quickly","left":401,"top":333,"width":77,"height":26},{"text":"sink","left":487,"top":333,"width":43,"height":20},{"text":"into","left":540,"top":335,"width":41,"height":18},{"text":"the","left":591,"top":333,"width":32,"height":20}]},{"text":"swampy goo. The dinosaur watches, bemused, as","left":99,"top":365,"words":[{"text":"swampy","left":99,"top":365,"width":89,"height":20},{"text":"goo.","left":195,"top":365,"width":44,"height":20},{"text":"The","left":247,"top":361,"width":41,"height":18},{"text":"dinosaur","left":295,"top":361,"width":93,"height":18},{"text":"watches,","left":395,"top":361,"width":89,"height":21},{"text":"bemused,","left":493,"top":361,"width":100,"height":21},{"text":"as","left":601,"top":367,"width":22,"height":14}]},{"text":"bubbles rise to mark your resting-place.","left":99,"top":387,"words":[{"text":"bubbles","left":99,"top":387,"width":81,"height":20},{"text":"rise","left":185,"top":388,"width":37,"height":19},{"text":"to","left":227,"top":390,"width":20,"height":17},{"text":"mark","left":252,"top":387,"width":54,"height":20},{"text":"your","left":311,"top":393,"width":49,"height":20},{"text":"resting-place.","left":365,"top":388,"width":137,"height":25}]},{"text":"96","left":350,"top":443,"words":[{"text":"96","left":350,"top":443,"width":24,"height":23}]},{"text":"In trying to open an Office marked 'Private', you","left":99,"top":468,"words":[{"text":"In","left":99,"top":468,"width":22,"height":19},{"text":"trying","left":131,"top":469,"width":62,"height":24},{"text":"to","left":203,"top":471,"width":20,"height":17},{"text":"open","left":232,"top":473,"width":52,"height":21},{"text":"an","left":293,"top":474,"width":26,"height":13},{"text":"Office","left":329,"top":469,"width":56,"height":19},{"text":"marked","left":394,"top":469,"width":78,"height":19},{"text":"'Private',","left":482,"top":469,"width":91,"height":22},{"text":"you","left":583,"top":475,"width":39,"height":19}]},{"text":"activate a security system. An electric shock pins","left":99,"top":496,"words":[{"text":"activate","left":99,"top":496,"width":80,"height":19},{"text":"a","left":187,"top":501,"width":12,"height":14},{"text":"security","left":208,"top":497,"width":82,"height":23},{"text":"system.","left":299,"top":498,"width":78,"height":23},{"text":"An","left":388,"top":496,"width":32,"height":19},{"text":"electric","left":429,"top":496,"width":72,"height":19},{"text":"shock","left":509,"top":496,"width":60,"height":19},{"text":"pins","left":579,"top":497,"width":44,"height":24}]},{"text":"you to the door-frame. By the time you get free, you","left":99,"top":527,"words":[{"text":"you","left":99,"top":527,"width":40,"height":20},{"text":"to","left":143,"top":525,"width":21,"height":16},{"text":"the","left":169,"top":522,"width":33,"height":19},{"text":"door-frame.","left":206,"top":522,"width":122,"height":19},{"text":"By","left":335,"top":523,"width":26,"height":24},{"text":"the","left":366,"top":523,"width":32,"height":18},{"text":"time","left":403,"top":523,"width":46,"height":19},{"text":"you","left":453,"top":528,"width":38,"height":20},{"text":"get","left":496,"top":525,"width":32,"height":23},{"text":"free,","left":533,"top":523,"width":44,"height":22},{"text":"you","left":583,"top":529,"width":39,"height":20}]},{"text":"have lost STAMINA point. Return to 85.","left":99,"top":549,"words":[{"text":"have","left":99,"top":549,"width":50,"height":20},{"text":"lost","left":154,"top":549,"width":38,"height":20},{"text":"STAMINA","left":213,"top":554,"width":101,"height":15},{"text":"point.","left":319,"top":550,"width":60,"height":25},{"text":"Return","left":387,"top":550,"width":70,"height":19},{"text":"to","left":463,"top":553,"width":20,"height":16},{"text":"85.","left":487,"top":551,"width":30,"height":23}]},{"text":"97","left":349,"top":609,"words":[{"text":"97","left":349,"top":609,"width":25,"height":19}]},{"text":"battle is over. You have torn the Man-trap Plant","left":143,"top":630,"words":[{"text":"battle","left":143,"top":630,"width":58,"height":19},{"text":"is","left":205,"top":631,"width":17,"height":19},{"text":"over.","left":226,"top":635,"width":52,"height":15},{"text":"You","left":283,"top":631,"width":42,"height":19},{"text":"have","left":331,"top":631,"width":49,"height":19},{"text":"torn","left":384,"top":633,"width":43,"height":17},{"text":"the","left":431,"top":631,"width":34,"height":19},{"text":"Man-trap","left":469,"top":631,"width":96,"height":25},{"text":"Plant","left":569,"top":631,"width":54,"height":19}]},{"text":"into a thousand pieces. Nothing remains of the","left":99,"top":658,"words":[{"text":"into","left":99,"top":658,"width":41,"height":19},{"text":"a","left":151,"top":663,"width":12,"height":14},{"text":"thousand","left":175,"top":657,"width":98,"height":20},{"text":"pieces.","left":284,"top":659,"width":70,"height":24},{"text":"Nothing","left":367,"top":658,"width":86,"height":25},{"text":"remains","left":465,"top":659,"width":82,"height":18},{"text":"of","left":557,"top":658,"width":22,"height":19},{"text":"the","left":590,"top":658,"width":33,"height":19}]},{"text":"vicious vegetable except a damper spot on the","left":99,"top":685,"words":[{"text":"vicious","left":99,"top":685,"width":73,"height":19},{"text":"vegetable","left":185,"top":685,"width":98,"height":25},{"text":"except","left":295,"top":687,"width":67,"height":23},{"text":"a","left":373,"top":690,"width":12,"height":14},{"text":"damper","left":399,"top":685,"width":80,"height":26},{"text":"spot","left":491,"top":688,"width":46,"height":23},{"text":"on","left":549,"top":691,"width":27,"height":14},{"text":"the","left":589,"top":686,"width":33,"height":19}]},{"text":"marshy ground. Turn to 237.","left":99,"top":711,"words":[{"text":"marshy","left":99,"top":711,"width":78,"height":26},{"text":"ground.","left":181,"top":712,"width":82,"height":25},{"text":"Turn","left":269,"top":711,"width":52,"height":20},{"text":"to","left":327,"top":715,"width":20,"height":16},{"text":"237.","left":351,"top":717,"width":40,"height":19}]}]}