{"inputPath":"D:\\Development\\robot-commando\\_book\\i.043.jpg","crop":{"x":318,"y":0,"width":638,"height":1082,"scale":2,"threshold":-1},"text":"114—116 1 You spy an open closet in an adjoining room. Inside you can see a medikit! You investigate; sure enough, the rest of your equipment is here! But as you are gathering it, a rifle-butt strikes your head from behind. Your adventure is over. 115 You hurriedly move to the side. The creature blun- ders past you and vanishes. You are on the outskirts of the City of the Jungle. If you re-enter the jungle, on the other path, turn to 73. If you want to go elsewhere, turn to 137. 116 If you have a flying robot, turn to 139. Otherwise, turn to 162.","lines":[{"text":"114—116","left":487,"top":59,"words":[{"text":"114—116","left":487,"top":59,"width":84,"height":22}]},{"text":"1","left":232,"top":151,"words":[{"text":"1","left":232,"top":151,"width":12,"height":41}]},{"text":"You spy an open closet in an adjoining room. Inside","left":51,"top":289,"words":[{"text":"You","left":51,"top":289,"width":41,"height":20},{"text":"spy","left":97,"top":295,"width":37,"height":19},{"text":"an","left":138,"top":295,"width":26,"height":13},{"text":"open","left":168,"top":294,"width":52,"height":20},{"text":"closet","left":225,"top":288,"width":59,"height":20},{"text":"in","left":288,"top":289,"width":20,"height":18},{"text":"an","left":312,"top":293,"width":26,"height":14},{"text":"adjoining","left":342,"top":288,"width":98,"height":25},{"text":"room.","left":444,"top":293,"width":60,"height":14},{"text":"Inside","left":509,"top":287,"width":64,"height":20}]},{"text":"you can see a medikit! You investigate; sure","left":51,"top":321,"words":[{"text":"you","left":51,"top":321,"width":38,"height":20},{"text":"can","left":105,"top":321,"width":37,"height":14},{"text":"see","left":159,"top":321,"width":34,"height":14},{"text":"a","left":207,"top":321,"width":12,"height":14},{"text":"medikit!","left":236,"top":316,"width":85,"height":19},{"text":"You","left":337,"top":315,"width":42,"height":19},{"text":"investigate;","left":395,"top":315,"width":118,"height":24},{"text":"sure","left":529,"top":319,"width":44,"height":14}]},{"text":"enough, the rest of your equipment is here! But as","left":51,"top":343,"words":[{"text":"enough,","left":51,"top":343,"width":85,"height":25},{"text":"the","left":144,"top":343,"width":33,"height":19},{"text":"rest","left":184,"top":345,"width":39,"height":16},{"text":"of","left":229,"top":342,"width":21,"height":19},{"text":"your","left":255,"top":347,"width":50,"height":20},{"text":"equipment","left":310,"top":343,"width":112,"height":23},{"text":"is","left":428,"top":342,"width":17,"height":19},{"text":"here!","left":452,"top":341,"width":50,"height":20},{"text":"But","left":510,"top":341,"width":36,"height":19},{"text":"as","left":551,"top":346,"width":22,"height":15}]},{"text":"you are gathering it, a rifle-butt strikes your head","left":51,"top":375,"words":[{"text":"you","left":51,"top":375,"width":40,"height":20},{"text":"are","left":97,"top":375,"width":34,"height":14},{"text":"gathering","left":138,"top":369,"width":100,"height":26},{"text":"it,","left":245,"top":370,"width":21,"height":20},{"text":"a","left":275,"top":375,"width":12,"height":13},{"text":"rifle-butt","left":295,"top":369,"width":90,"height":19},{"text":"strikes","left":393,"top":368,"width":66,"height":20},{"text":"your","left":467,"top":373,"width":49,"height":20},{"text":"head","left":523,"top":368,"width":50,"height":19}]},{"text":"from behind. Your adventure is over.","left":52,"top":396,"words":[{"text":"from","left":52,"top":396,"width":48,"height":20},{"text":"behind.","left":105,"top":397,"width":80,"height":19},{"text":"Your","left":191,"top":397,"width":52,"height":18},{"text":"adventure","left":247,"top":396,"width":106,"height":19},{"text":"is","left":357,"top":397,"width":17,"height":18},{"text":"over.","left":379,"top":401,"width":51,"height":14}]},{"text":"115","left":295,"top":455,"words":[{"text":"115","left":295,"top":455,"width":36,"height":19}]},{"text":"You hurriedly move to the side. The creature blun-","left":52,"top":477,"words":[{"text":"You","left":52,"top":477,"width":41,"height":20},{"text":"hurriedly","left":99,"top":477,"width":98,"height":26},{"text":"move","left":203,"top":483,"width":56,"height":14},{"text":"to","left":265,"top":479,"width":21,"height":17},{"text":"the","left":292,"top":477,"width":33,"height":19},{"text":"side.","left":330,"top":477,"width":48,"height":19},{"text":"The","left":385,"top":477,"width":40,"height":18},{"text":"creature","left":430,"top":479,"width":84,"height":16},{"text":"blun-","left":520,"top":475,"width":55,"height":20}]},{"text":"ders past you and vanishes. You are on the outskirts","left":52,"top":505,"words":[{"text":"ders","left":52,"top":505,"width":43,"height":19},{"text":"past","left":100,"top":507,"width":44,"height":23},{"text":"you","left":148,"top":510,"width":38,"height":19},{"text":"and","left":191,"top":504,"width":39,"height":19},{"text":"vanishes.","left":235,"top":504,"width":96,"height":19},{"text":"You","left":336,"top":504,"width":41,"height":19},{"text":"are","left":381,"top":509,"width":32,"height":14},{"text":"on","left":417,"top":509,"width":26,"height":14},{"text":"the","left":448,"top":504,"width":33,"height":19},{"text":"outskirts","left":484,"top":504,"width":91,"height":19}]},{"text":"of the City of the Jungle. If you re-enter the jungle,","left":52,"top":532,"words":[{"text":"of","left":52,"top":532,"width":21,"height":19},{"text":"the","left":79,"top":532,"width":32,"height":19},{"text":"City","left":117,"top":532,"width":43,"height":25},{"text":"of","left":167,"top":531,"width":21,"height":20},{"text":"the","left":193,"top":531,"width":33,"height":20},{"text":"Jungle.","left":230,"top":531,"width":73,"height":25},{"text":"If","left":311,"top":531,"width":16,"height":19},{"text":"you","left":332,"top":536,"width":39,"height":19},{"text":"re-enter","left":377,"top":534,"width":82,"height":15},{"text":"the","left":464,"top":531,"width":33,"height":18},{"text":"jungle,","left":501,"top":530,"width":72,"height":25}]},{"text":"on the other path, turn to 73. If you want to go","left":52,"top":563,"words":[{"text":"on","left":52,"top":563,"width":26,"height":14},{"text":"the","left":88,"top":559,"width":33,"height":18},{"text":"other","left":131,"top":559,"width":56,"height":18},{"text":"path,","left":196,"top":558,"width":53,"height":26},{"text":"turn","left":261,"top":561,"width":44,"height":16},{"text":"to","left":315,"top":560,"width":20,"height":17},{"text":"73.","left":343,"top":563,"width":30,"height":19},{"text":"If","left":384,"top":557,"width":17,"height":20},{"text":"you","left":409,"top":563,"width":39,"height":20},{"text":"want","left":457,"top":560,"width":53,"height":16},{"text":"to","left":519,"top":560,"width":20,"height":16},{"text":"go","left":549,"top":562,"width":26,"height":21}]},{"text":"elsewhere, turn to 137.","left":53,"top":585,"words":[{"text":"elsewhere,","left":53,"top":585,"width":110,"height":22},{"text":"turn","left":170,"top":588,"width":43,"height":17},{"text":"to","left":219,"top":588,"width":20,"height":17},{"text":"137.","left":244,"top":591,"width":41,"height":18}]},{"text":"116","left":297,"top":639,"words":[{"text":"116","left":297,"top":639,"width":35,"height":19}]},{"text":"If you have a flying robot, turn to 139. Otherwise,","left":53,"top":667,"words":[{"text":"If","left":53,"top":667,"width":16,"height":18},{"text":"you","left":75,"top":672,"width":38,"height":20},{"text":"have","left":121,"top":667,"width":50,"height":18},{"text":"a","left":177,"top":672,"width":12,"height":13},{"text":"flying","left":197,"top":667,"width":60,"height":24},{"text":"robot,","left":264,"top":666,"width":61,"height":22},{"text":"turn","left":333,"top":668,"width":44,"height":17},{"text":"to","left":385,"top":668,"width":20,"height":17},{"text":"139.","left":411,"top":671,"width":40,"height":18},{"text":"Otherwise,","left":460,"top":665,"width":113,"height":22}]},{"text":"turn to 162.","left":54,"top":696,"words":[{"text":"turn","left":54,"top":696,"width":42,"height":17},{"text":"to","left":103,"top":697,"width":20,"height":16},{"text":"162.","left":127,"top":695,"width":41,"height":18}]}]}