{"inputPath":"D:\\Development\\robot-commando\\_book\\i.073.jpg","crop":{"x":318,"y":0,"width":638,"height":1074,"scale":2,"threshold":-1},"text":"239—241 239 You attack the Iguanodon that is blocking your way. This plant-eating dinosaur walks on two legs. It is tough and heavy-set, and its spiky 'thumbs' are good weapons. IGUANODON SPEED Medium ARMOUR 5 SXtLL9 You cannot Escape. If you defeat the Iguanodon, tum to 137. If your robot's ARMOUR is reduced to o, turn to 306. 240 The tunnel winds until you have lost all sense Of direction. Then it forks. One fork seems to go up; the other turns downward. If you go up, turn to 72. If you go down, tum to 15. 241 Your captors do not even discuss what to do with you; they stand you against a wall and shoot you as a spy. Your adventure is over.","lines":[{"text":"239—241","left":479,"top":61,"words":[{"text":"239—241","left":479,"top":61,"width":84,"height":20}]},{"text":"239","left":285,"top":385,"words":[{"text":"239","left":285,"top":385,"width":34,"height":19}]},{"text":"You attack the Iguanodon that is blocking your way.","left":42,"top":405,"words":[{"text":"You","left":42,"top":405,"width":39,"height":20},{"text":"attack","left":85,"top":406,"width":62,"height":19},{"text":"the","left":152,"top":407,"width":32,"height":18},{"text":"Iguanodon","left":189,"top":407,"width":111,"height":25},{"text":"that","left":306,"top":407,"width":40,"height":19},{"text":"is","left":349,"top":407,"width":17,"height":20},{"text":"blocking","left":369,"top":407,"width":88,"height":26},{"text":"your","left":460,"top":413,"width":49,"height":19},{"text":"way.","left":512,"top":413,"width":49,"height":20}]},{"text":"This plant-eating dinosaur walks on two legs. It is","left":41,"top":433,"words":[{"text":"This","left":41,"top":433,"width":44,"height":19},{"text":"plant-eating","left":92,"top":433,"width":125,"height":26},{"text":"dinosaur","left":224,"top":434,"width":92,"height":19},{"text":"walks","left":323,"top":434,"width":59,"height":19},{"text":"on","left":389,"top":439,"width":26,"height":14},{"text":"two","left":423,"top":437,"width":39,"height":16},{"text":"legs.","left":468,"top":435,"width":47,"height":24},{"text":"It","left":524,"top":435,"width":15,"height":18},{"text":"is","left":546,"top":435,"width":17,"height":19}]},{"text":"tough and heavy-set, and its spiky 'thumbs' are","left":42,"top":460,"words":[{"text":"tough","left":42,"top":460,"width":59,"height":24},{"text":"and","left":111,"top":461,"width":40,"height":18},{"text":"heavy-set,","left":162,"top":461,"width":105,"height":25},{"text":"and","left":279,"top":461,"width":38,"height":19},{"text":"its","left":329,"top":462,"width":24,"height":19},{"text":"spiky","left":363,"top":461,"width":56,"height":26},{"text":"'thumbs'","left":430,"top":461,"width":89,"height":20},{"text":"are","left":530,"top":467,"width":33,"height":14}]},{"text":"good weapons.","left":41,"top":488,"words":[{"text":"good","left":41,"top":488,"width":50,"height":23},{"text":"weapons.","left":97,"top":493,"width":99,"height":20}]},{"text":"IGUANODON","left":42,"top":527,"words":[{"text":"IGUANODON","left":42,"top":527,"width":153,"height":20}]},{"text":"SPEED Medium","left":241,"top":559,"words":[{"text":"SPEED","left":241,"top":559,"width":66,"height":16},{"text":"Medium","left":312,"top":555,"width":87,"height":20}]},{"text":"ARMOUR 5","left":63,"top":559,"words":[{"text":"ARMOUR","left":63,"top":559,"width":94,"height":15},{"text":"5","left":161,"top":561,"width":12,"height":18}]},{"text":"SXtLL9","left":485,"top":561,"words":[{"text":"SXtLL9","left":485,"top":561,"width":78,"height":19}]},{"text":"You cannot Escape. If you defeat the Iguanodon,","left":41,"top":594,"words":[{"text":"You","left":41,"top":594,"width":40,"height":20},{"text":"cannot","left":91,"top":598,"width":71,"height":17},{"text":"Escape.","left":173,"top":595,"width":67,"height":25},{"text":"If","left":252,"top":595,"width":17,"height":20},{"text":"you","left":277,"top":601,"width":39,"height":20},{"text":"defeat","left":326,"top":595,"width":64,"height":20},{"text":"the","left":400,"top":595,"width":33,"height":20},{"text":"Iguanodon,","left":442,"top":596,"width":119,"height":25}]},{"text":"tum to 137. If your robot's ARMOUR is reduced to o,","left":41,"top":624,"words":[{"text":"tum","left":41,"top":624,"width":43,"height":17},{"text":"to","left":89,"top":625,"width":20,"height":16},{"text":"137.","left":114,"top":627,"width":41,"height":19},{"text":"If","left":161,"top":622,"width":16,"height":19},{"text":"your","left":181,"top":628,"width":50,"height":19},{"text":"robot's","left":235,"top":623,"width":70,"height":20},{"text":"ARMOUR","left":310,"top":627,"width":94,"height":16},{"text":"is","left":409,"top":624,"width":16,"height":19},{"text":"reduced","left":430,"top":624,"width":83,"height":19},{"text":"to","left":519,"top":626,"width":19,"height":17},{"text":"o,","left":542,"top":629,"width":19,"height":16}]},{"text":"turn to 306.","left":41,"top":651,"words":[{"text":"turn","left":41,"top":651,"width":42,"height":17},{"text":"to","left":89,"top":651,"width":21,"height":18},{"text":"306.","left":114,"top":651,"width":41,"height":22}]},{"text":"240","left":285,"top":709,"words":[{"text":"240","left":285,"top":709,"width":34,"height":18}]},{"text":"The tunnel winds until you have lost all sense Of","left":39,"top":729,"words":[{"text":"The","left":39,"top":729,"width":40,"height":20},{"text":"tunnel","left":88,"top":730,"width":67,"height":19},{"text":"winds","left":164,"top":731,"width":63,"height":18},{"text":"until","left":237,"top":731,"width":48,"height":18},{"text":"you","left":293,"top":736,"width":39,"height":19},{"text":"have","left":341,"top":731,"width":50,"height":19},{"text":"lost","left":399,"top":731,"width":37,"height":19},{"text":"all","left":443,"top":731,"width":24,"height":19},{"text":"sense","left":476,"top":737,"width":57,"height":14},{"text":"Of","left":541,"top":731,"width":22,"height":20}]},{"text":"direction. Then it forks. One fork seems to go up;","left":41,"top":756,"words":[{"text":"direction.","left":41,"top":756,"width":96,"height":21},{"text":"Then","left":145,"top":757,"width":54,"height":20},{"text":"it","left":208,"top":758,"width":14,"height":19},{"text":"forks.","left":229,"top":757,"width":58,"height":20},{"text":"One","left":296,"top":757,"width":45,"height":20},{"text":"fork","left":348,"top":757,"width":42,"height":20},{"text":"seems","left":397,"top":763,"width":63,"height":14},{"text":"to","left":468,"top":761,"width":20,"height":16},{"text":"go","left":495,"top":764,"width":26,"height":19},{"text":"up;","left":528,"top":763,"width":33,"height":20}]},{"text":"the other turns downward. If you go up, turn to 72.","left":41,"top":783,"words":[{"text":"the","left":41,"top":783,"width":32,"height":20},{"text":"other","left":77,"top":784,"width":56,"height":19},{"text":"turns","left":138,"top":787,"width":54,"height":16},{"text":"downward.","left":197,"top":785,"width":119,"height":18},{"text":"If","left":323,"top":785,"width":15,"height":18},{"text":"you","left":342,"top":790,"width":39,"height":20},{"text":"go","left":387,"top":791,"width":26,"height":20},{"text":"up,","left":417,"top":791,"width":34,"height":20},{"text":"turn","left":457,"top":787,"width":44,"height":18},{"text":"to","left":507,"top":788,"width":20,"height":17},{"text":"72.","left":531,"top":791,"width":29,"height":18}]},{"text":"If you go down, tum to 15.","left":41,"top":810,"words":[{"text":"If","left":41,"top":810,"width":14,"height":19},{"text":"you","left":59,"top":816,"width":39,"height":19},{"text":"go","left":103,"top":817,"width":27,"height":20},{"text":"down,","left":135,"top":812,"width":66,"height":21},{"text":"tum","left":208,"top":813,"width":43,"height":18},{"text":"to","left":257,"top":814,"width":20,"height":17},{"text":"15.","left":282,"top":817,"width":29,"height":19}]},{"text":"241","left":284,"top":871,"words":[{"text":"241","left":284,"top":871,"width":35,"height":18}]},{"text":"Your captors do not even discuss what to do with","left":40,"top":891,"words":[{"text":"Your","left":40,"top":891,"width":51,"height":20},{"text":"captors","left":97,"top":896,"width":76,"height":21},{"text":"do","left":180,"top":893,"width":27,"height":19},{"text":"not","left":215,"top":895,"width":34,"height":17},{"text":"even","left":255,"top":898,"width":50,"height":14},{"text":"discuss","left":312,"top":893,"width":75,"height":20},{"text":"what","left":395,"top":893,"width":51,"height":19},{"text":"to","left":454,"top":896,"width":20,"height":17},{"text":"do","left":481,"top":893,"width":27,"height":20},{"text":"with","left":515,"top":893,"width":46,"height":20}]},{"text":"you; they stand you against a wall and shoot you as","left":40,"top":923,"words":[{"text":"you;","left":40,"top":923,"width":44,"height":20},{"text":"they","left":90,"top":919,"width":46,"height":25},{"text":"stand","left":141,"top":919,"width":57,"height":20},{"text":"you","left":203,"top":925,"width":39,"height":20},{"text":"against","left":247,"top":921,"width":74,"height":24},{"text":"a","left":325,"top":925,"width":12,"height":14},{"text":"wall","left":342,"top":920,"width":43,"height":19},{"text":"and","left":390,"top":920,"width":39,"height":19},{"text":"shoot","left":434,"top":920,"width":57,"height":19},{"text":"you","left":495,"top":925,"width":40,"height":20},{"text":"as","left":539,"top":925,"width":22,"height":14}]},{"text":"a spy. Your adventure is over.","left":39,"top":951,"words":[{"text":"a","left":39,"top":951,"width":12,"height":13},{"text":"spy.","left":55,"top":951,"width":43,"height":20},{"text":"Your","left":105,"top":946,"width":52,"height":19},{"text":"adventure","left":161,"top":947,"width":106,"height":19},{"text":"is","left":272,"top":948,"width":17,"height":18},{"text":"over.","left":293,"top":952,"width":53,"height":15}]}]}